noop.cpython-311-darwin.so
sqlite_jsonschema/__init__.py
sqlite_jsonschema/jsonschema0.dylib
sqlite_jsonschema/version.py
sqlite_jsonschema-0.2.3.dist-info/METADATA
sqlite_jsonschema-0.2.3.dist-info/WHEEL
sqlite_jsonschema-0.2.3.dist-info/top_level.txt
sqlite_jsonschema-0.2.3.dist-info/RECORD
