Metadata-Version: 2.1
Name: sqlite-jsonschema
Version: 0.2.3
Home-page: https://github.com/asg017/sqlite-jsonschema
Author: Alex Garcia
License: MIT License, Apache License, Version 2.0
Project-URL: Issues, https://github.com/asg017/sqlite-jsonschema/issues
Project-URL: CI, https://github.com/asg017/sqlite-jsonschema/actions
Project-URL: Changelog, https://github.com/asg017/sqlite-jsonschema/releases
Requires-Python: >=3.7
Provides-Extra: test
Requires-Dist: pytest ; extra == 'test'
